src/__init__.py
src/endpoints/__init__.py
src/endpoints/user.py
src/endpoints/vars.py
src/endpoints/workspace.py
src/tests/__init__.py
src/tests/set_envs.py
src/tests/test_endpoint_specification.py
lib_bitbucket_cloud-0.0.2.dist-info/LICENCE
lib_bitbucket_cloud-0.0.2.dist-info/METADATA
lib_bitbucket_cloud-0.0.2.dist-info/WHEEL
lib_bitbucket_cloud-0.0.2.dist-info/top_level.txt
lib_bitbucket_cloud-0.0.2.dist-info/RECORD
